almatasks/LICENSE.txt
almatasks/__init__.py
almatasks/wvrgcal.py
almatasks/__bin__/wvrgcal
almatasks/gotasks/__init__.py
almatasks/gotasks/wvrgcal.py
almatasks/private/__init__.py
almatasks/private/task_wvrgcal.py
almatasks-1.7.1.dist-info/METADATA
almatasks-1.7.1.dist-info/WHEEL
almatasks-1.7.1.dist-info/top_level.txt
almatasks-1.7.1.dist-info/RECORD
