Metadata-Version: 2.1
Name: almatasks
Version: 1.7.1
Summary: ALMA tasks (inc wvrgcal)
Home-page: https://open-bitbucket.nrao.edu/projects/CASA/repos/almatasks/browse
Author: CASA development team
Author-email: aips2-request@nrao.edu
Maintainer: Darrell Schiebel
Maintainer-email: drs@nrao.edu
License: GNU Library or Lesser General Public License (LGPL)
Download-URL: https://casa.nrao.edu/download/
Platform: UNKNOWN
Classifier: Programming Language :: Python :: 3
Requires-Dist: casatasks
Requires-Dist: casatools
